lietorch/__init__.py
lietorch/bspline.py
lietorch/generic.py
lietorch/padding.py
lietorch/lib/liblietorch.so
lietorch/lib/lietorch.dll
lietorch/models/__init__.py
lietorch/models/dca1.py
lietorch/models/drive.py
lietorch/models/ds_pde.py
lietorch/models/fixed_lift.py
lietorch/models/rotnist.py
lietorch/nn/__init__.py
lietorch/nn/functional.py
lietorch/nn/loss.py
lietorch/nn/m2.py
lietorch/nn/r2.py
tests/__init__.py
tests/test_backend.py
tests/test_bspline.py
tests/test_grayscale_morph.py
tests/test_m2.py
tests/test_r2.py
lietorch-0.8.2.dist-info/AUTHORS
lietorch-0.8.2.dist-info/LICENSE
lietorch-0.8.2.dist-info/METADATA
lietorch-0.8.2.dist-info/WHEEL
lietorch-0.8.2.dist-info/top_level.txt
lietorch-0.8.2.dist-info/RECORD
