Metadata-Version: 2.1
Name: lietorch
Version: 0.8.2
Summary: PDE-G-CNN package for PyTorch
Home-page: https://gitlab.com/bsmetsjr/lietorch
Author: B.M.N. Smets et.al
Author-email: b.m.n.smets@tue.nl
Classifier: Programming Language :: Python :: 3
Classifier: Programming Language :: C++
Classifier: Development Status :: 4 - Beta
Classifier: License :: OSI Approved :: MIT License
Classifier: Operating System :: Microsoft :: Windows
Classifier: Operating System :: POSIX :: Linux
Classifier: Environment :: GPU :: NVIDIA CUDA
Classifier: Intended Audience :: Developers
Classifier: Intended Audience :: Education
Classifier: Intended Audience :: Science/Research
Classifier: Topic :: Scientific/Engineering :: Mathematics
Classifier: Topic :: Scientific/Engineering :: Artificial Intelligence
Requires-Python: >=3.12
License-File: LICENSE
License-File: AUTHORS
Requires-Dist: torch ==2.6.*
Requires-Dist: torchvision ==0.21.*
